{
    "customerId":"FSRTESTINGCODECID12345==",
    "notificationType": "IN_SESSION",
    "measures":
    [
        {
            "surveyId": "iphone_app_QA",
            "surveyStyle": "modern",
            "daysSinceLaunch": 0,
            "launchCount": 0,
            "significantEventThresholds":
            {
                "app_test_1": 4
            }
        }
    ],
    "invite": {
        "logo": "ForeSee_logo",
        "baseColor": [237, 38, 54]
    },
    "survey": {
        "closeButtonColor": [255, 255, 255],
        "closeButtonBackgroundColor": [65, 65, 65],
        "headerColor": [65, 65, 65]
    }
}
